NERDA_framework/__init__.py
NERDA_framework/datasets.py
NERDA_framework/models.py
NERDA_framework/networks.py
NERDA_framework/performance.py
NERDA_framework/precooked.py
NERDA_framework/predictions.py
NERDA_framework/preprocessing.py
NERDA_framework/training.py
NERDA_framework/utils.py
NERP/__init__.py
NERP/compile_model.py
NERP/inference.py
NERP/models.py
NERP/prepare_data.py
NERP/training.py
NERP/utils.py
NERP-1.0.2.2.dist-info/LICENSE
NERP-1.0.2.2.dist-info/METADATA
NERP-1.0.2.2.dist-info/WHEEL
NERP-1.0.2.2.dist-info/top_level.txt
NERP-1.0.2.2.dist-info/RECORD
