Metadata-Version: 2.1
Name: NERP
Version: 1.0.2.2
Summary: A pipeline for fine-tuning pre-trained transformers for Named Entity Recognition (NER) tasks
Home-page: https://github.com/chaarangan/NERP
Author: Charangan Vasantharajan
Author-email: chaanuv@gmail.com
License: LICENSE.txt
Platform: UNKNOWN
Classifier: Programming Language :: Python :: 3
Classifier: License :: OSI Approved :: MIT License
Requires-Python: >=3.7
License-File: LICENSE
Requires-Dist: torch
Requires-Dist: transformers
Requires-Dist: joblib
Requires-Dist: nltk
Requires-Dist: pandas
Requires-Dist: progressbar
Requires-Dist: pyconll
Requires-Dist: PyYAML
Requires-Dist: scipy
Requires-Dist: sentencepiece
Requires-Dist: threadpoolctl
Requires-Dist: scikit-learn
Requires-Dist: TorchCRF
